gocept.pytestlayer-8.1.1-py3.11-nspkg.pth
gocept/pytestlayer/__init__.py
gocept/pytestlayer/doctest.py
gocept/pytestlayer/fixture.py
gocept/pytestlayer/layered.py
gocept/pytestlayer/plugin.py
gocept/pytestlayer/testing.py
gocept.pytestlayer-8.1.1.dist-info/LICENSE.txt
gocept.pytestlayer-8.1.1.dist-info/METADATA
gocept.pytestlayer-8.1.1.dist-info/WHEEL
gocept.pytestlayer-8.1.1.dist-info/entry_points.txt
gocept.pytestlayer-8.1.1.dist-info/namespace_packages.txt
gocept.pytestlayer-8.1.1.dist-info/top_level.txt
gocept.pytestlayer-8.1.1.dist-info/RECORD
